devboard-0.1.0.dist-info/METADATA
devboard-0.1.0.dist-info/WHEEL
devboard-0.1.0.dist-info/entry_points.txt
devboard-0.1.0.dist-info/licenses/LICENSE
devboard/__init__.py
devboard/__main__.py
devboard/_internal/__init__.py
devboard/_internal/app.py
devboard/_internal/board.py
devboard/_internal/cli.py
devboard/_internal/datatable.py
devboard/_internal/debug.py
devboard/_internal/default_board.py
devboard/_internal/devboard.tcss
devboard/_internal/modal.py
devboard/_internal/notifications.py
devboard/_internal/projects.py
devboard/py.typed
devboard-0.1.0.dist-info/RECORD
